waldur_auth_social/__init__.py
waldur_auth_social/apps.py
waldur_auth_social/extension.py
waldur_auth_social/handlers.py
waldur_auth_social/log.py
waldur_auth_social/models.py
waldur_auth_social/serializers.py
waldur_auth_social/tasks.py
waldur_auth_social/urls.py
waldur_auth_social/views.py
waldur_auth_social/migrations/0001_initial.py
waldur_auth_social/migrations/__init__.py
waldur_auth_social/templates/nodeconductor_auth_social/activation_email_body.txt
waldur_auth_social-0.7.4.dist-info/DESCRIPTION.rst
waldur_auth_social-0.7.4.dist-info/METADATA
waldur_auth_social-0.7.4.dist-info/RECORD
waldur_auth_social-0.7.4.dist-info/WHEEL
waldur_auth_social-0.7.4.dist-info/entry_points.txt
waldur_auth_social-0.7.4.dist-info/metadata.json
waldur_auth_social-0.7.4.dist-info/top_level.txt
